fa/fa.v
// 1-bit Full Adder using two Half Adders

module ha(
    input  wire a,
    input  wire b,
    output wire sum,
    output wire carry
);
    assign sum   = a ^ b;
    assign carry = a & b;
endmodule

module fa(
    input  wire a,
    input  wire b,
    input  wire cin,
    output wire sum,
    output wire cout
);
    wire sum1, carry1, carry2;

    // First half adder
    ha ha1 (
        .a(a),
        .b(b),
        .sum(sum1),
        .carry(carry1)
    );

    // Second half adder
    ha ha2 (
        .a(sum1),
        .b(cin),
        .sum(sum),
        .carry(carry2)
    );

    assign cout = carry1 | carry2;
endmodule

fa/tb_fa.v
// Testbench for 1-bit Full Adder

module tb_fa;
    reg a, b, cin;
    wire sum, cout;

    // Instantiate the full adder
    fa uut (
        .a(a),
        .b(b),
        .cin(cin),
        .sum(sum),
        .cout(cout)
    );

    initial begin
        $dumpfile("fa_tb.vcd");
        $dumpvars(0, tb_fa);
        $display("A B CIN | SUM COUT");
        $display("------------------");
        a = 0; b = 0; cin = 0; #10;
        $display("%b %b  %b  |  %b   %b", a, b, cin, sum, cout);
        a = 0; b = 0; cin = 1; #10;
        $display("%b %b  %b  |  %b   %b", a, b, cin, sum, cout);
        a = 0; b = 1; cin = 0; #10;
        $display("%b %b  %b  |  %b   %b", a, b, cin, sum, cout);
        a = 0; b = 1; cin = 1; #10;
        $display("%b %b  %b  |  %b   %b", a, b, cin, sum, cout);
        a = 1; b = 0; cin = 0; #10;
        $display("%b %b  %b  |  %b   %b", a, b, cin, sum, cout);
        a = 1; b = 0; cin = 1; #10;
        $display("%b %b  %b  |  %b   %b", a, b, cin, sum, cout);
        a = 1; b = 1; cin = 0; #10;
        $display("%b %b  %b  |  %b   %b", a, b, cin, sum, cout);
        a = 1; b = 1; cin = 1; #10;
        $display("%b %b  %b  |  %b   %b", a, b, cin, sum, cout);
        $finish;
    end
endmodule

fa/fa_tb.vcd
$date
	Thu May 29 07:51:31 2025
$end
$version
	Icarus Verilog
$end
$timescale
	1s
$end
$scope module tb_fa $end
$var wire 1 ! sum $end
$var wire 1 " cout $end
$var reg 1 # a $end
$var reg 1 $ b $end
$var reg 1 % cin $end
$scope module uut $end
$var wire 1 # a $end
$var wire 1 $ b $end
$var wire 1 % cin $end
$var wire 1 " cout $end
$var wire 1 & sum1 $end
$var wire 1 ! sum $end
$var wire 1 ' carry2 $end
$var wire 1 ( carry1 $end
$scope module ha1 $end
$var wire 1 # a $end
$var wire 1 $ b $end
$var wire 1 ( carry $end
$var wire 1 & sum $end
$upscope $end
$scope module ha2 $end
$var wire 1 & a $end
$var wire 1 % b $end
$var wire 1 ' carry $end
$var wire 1 ! sum $end
$upscope $end
$upscope $end
$upscope $end
$enddefinitions $end
#0
$dumpvars
0(
0'
0&
0%
0$
0#
0"
0!
$end
#10
1!
1%
#20
1&
0%
1$
#30
1"
0!
1'
1%
#40
0"
1!
0'
0%
0$
1#
#50
1"
0!
1'
1%
#60
0'
0&
1(
0%
1$
#70
1!
1%
